{
  "$schema": "../gen/schemas/desktop-schema.json",
  "identifier": "default",
  "description": "Capability for the main window",
  "windows": ["main", "settings"],
  "permissions": [
    "core:default",
    "dialog:default",
    "fs:default",
    "fs:allow-write-text-file",
    "fs:allow-read-text-file",
    "fs:allow-home-read-recursive",
    "fs:allow-home-write-recursive",
    
    "core:window:allow-create",
    "core:window:allow-center",
    "core:window:allow-set-focus",
    "core:window:allow-close",
    
    "core:webview:allow-create-webview-window",
    
    "core:event:default"
  ]
}